mpl_typst/__init__.py
mpl_typst/as_default.py
mpl_typst/backend.py
mpl_typst/backend_test.py
mpl_typst/config.py
mpl_typst/config_test.py
mpl_typst/prologue.typ
mpl_typst/typst.py
mpl_typst/typst_test.py
mpl_typst-0.2.1.dist-info/licenses/LICENSE
mpl_typst-0.2.1.dist-info/METADATA
mpl_typst-0.2.1.dist-info/WHEEL
mpl_typst-0.2.1.dist-info/top_level.txt
mpl_typst-0.2.1.dist-info/zip-safe
mpl_typst-0.2.1.dist-info/RECORD
