Metadata-Version: 2.4
Name: mpl-typst
Version: 0.2.1
Summary: Typst backend for matplotlib (Python visualization library).
Author-email: Daniel Bershatsky <daniel.bershatsky@gmail.com>
License: MIT
Project-URL: Homepage, https://github.com/daskol/mpl-typst
Project-URL: Repository, https://github.com/daskol/mpl-typst
Project-URL: Issues, https://github.com/daskol/mpl-typst/issues
Classifier: Development Status :: 5 - Production/Stable
Classifier: Environment :: Other Environment
Classifier: Intended Audience :: Developers
Classifier: Intended Audience :: Education
Classifier: Intended Audience :: End Users/Desktop
Classifier: Intended Audience :: Information Technology
Classifier: Intended Audience :: Science/Research
Classifier: License :: OSI Approved :: MIT License
Classifier: Natural Language :: English
Classifier: Operating System :: OS Independent
Classifier: Programming Language :: Python
Classifier: Programming Language :: Python :: 3
Classifier: Programming Language :: Python :: 3.11
Classifier: Programming Language :: Python :: 3.12
Classifier: Topic :: Scientific/Engineering
Classifier: Topic :: Scientific/Engineering :: Visualization
Classifier: Topic :: Text Processing
Classifier: Topic :: Text Processing :: Markup
Classifier: Topic :: Utilities
Classifier: Typing :: Typed
Requires-Python: <4,>=3.11
License-File: LICENSE
Requires-Dist: matplotlib>=3.8
Requires-Dist: numpy>=1.21
Requires-Dist: numpy>=1.21.2; python_version >= "3.10"
Requires-Dist: numpy>=1.23.3; python_version >= "3.11"
Requires-Dist: numpy>=1.26.0; python_version >= "3.12"
Requires-Dist: numpy>=2.1.0; python_version >= "3.13"
Provides-Extra: dev
Requires-Dist: isort; extra == "dev"
Requires-Dist: pytest>=8; extra == "dev"
Requires-Dist: ruff; extra == "dev"
Provides-Extra: test
Requires-Dist: pillow; extra == "test"
Requires-Dist: numpy; extra == "test"
Dynamic: license-file
